scope/__init__.py
scope/batch.py
scope/scopemath.py
scope/simulatetarget.py
scope/version.py
tele_scope-1.0.5.dist-info/METADATA
tele_scope-1.0.5.dist-info/RECORD
tele_scope-1.0.5.dist-info/WHEEL
tele_scope-1.0.5.dist-info/top_level.txt
