Metadata-Version: 2.1
Name: tele-scope
Version: 1.0.5
Summary: Simulated CCD Observations for Photometric Experimentation
Home-page: https://github.com/nksaunders/scope
Author: Nicholas Saunders
Author-email: nks1994@uw.edu
License: MIT
Platform: UNKNOWN
Classifier: License :: OSI Approved :: MIT License
Classifier: Programming Language :: Python
Classifier: Programming Language :: Python :: 3
Classifier: Topic :: Scientific/Engineering :: Astronomy
Requires-Dist: everest-pipeline
Requires-Dist: astroML
